setup.cfg
setup.py
linaro_django_jsonfield/__init__.py
linaro_django_jsonfield/forms.py
linaro_django_jsonfield/models.py
linaro_django_jsonfield.egg-info/PKG-INFO
linaro_django_jsonfield.egg-info/SOURCES.txt
linaro_django_jsonfield.egg-info/dependency_links.txt
linaro_django_jsonfield.egg-info/requires.txt
linaro_django_jsonfield.egg-info/top_level.txt
linaro_django_jsonfield.egg-info/zip-safe