Metadata-Version: 1.0
Name: linaro-django-jsonfield
Version: 0.3
Summary: Django's missing JSON field similar to XMLField
Home-page: https://launchpad.net/django-jsonfield
Author: Zygmunt Krynicki
Author-email: zygmunt.krynicki@linaro.org
License: LGPLv3
Keywords: django,json,field
Platform: UNKNOWN
Classifier: Development Status :: 3 - Alpha
Classifier: License :: OSI Approved :: GNU Library or Lesser General Public License (LGPL)
Classifier: Operating System :: OS Independent
Classifier: Programming Language :: Python :: 2.6
Classifier: Environment :: Web Environment
Classifier: Framework :: Django
Classifier: Intended Audience :: Developers
